stateplane/__init__.py
stateplane/__main__.py
stateplane/countyfp.csv
stateplane/dicts.py
stateplane/stateplane.geojson
stateplane/stateplane.py
stateplane-0.5.0.dist-info/LICENSE
stateplane-0.5.0.dist-info/METADATA
stateplane-0.5.0.dist-info/WHEEL
stateplane-0.5.0.dist-info/entry_points.txt
stateplane-0.5.0.dist-info/top_level.txt
stateplane-0.5.0.dist-info/zip-safe
stateplane-0.5.0.dist-info/RECORD
