Metadata-Version: 2.1
Name: stateplane
Version: 0.5.0
Summary: Find the state plane projection for a point or locale
Author-email: Neil Freeman <contact@fakeisthenewreal.org>
License: GNU GENERAL PUBLIC LICENSE
Project-URL: Homepage, https://github.com/fitnr/stateplane
Keywords: gis,usa,projection
Classifier: Development Status :: 4 - Beta
Classifier: Intended Audience :: Developers
Classifier: Programming Language :: Python :: 3.7
Classifier: Programming Language :: Python :: 3.8
Classifier: Programming Language :: Python :: 3.9
Classifier: Operating System :: OS Independent
Classifier: License :: OSI Approved :: GNU General Public License v3 (GPLv3)
Requires-Python: >=3.7
License-File: LICENSE
Requires-Dist: shapely
Requires-Dist: pyproj (>=3.2.0)
Requires-Dist: importlib-resources ; python_version < "3.9"
Provides-Extra: testing
Requires-Dist: coverage[toml] (>=6) ; extra == 'testing'
Requires-Dist: pylint (>=2.12.2) ; extra == 'testing'
